mg_file/__init__.py
mg_file/castom_type/README.md
mg_file/castom_type/__init__.py
mg_file/castom_type/base.py
mg_file/castom_type/test/test.py
mg_file/file/__init__.py
mg_file/file/base_file.py
mg_file/file/base_folder.py
mg_file/file/csv_file.py
mg_file/file/env_file.py
mg_file/file/helpful.py
mg_file/file/json_file.py
mg_file/file/log_file.py
mg_file/file/pickle_file.py
mg_file/file/test/__init__.py
mg_file/file/test/data_set/__env.env
mg_file/file/test/test_base.py
mg_file/file/test/test_csv.py
mg_file/file/test/test_env_file.py
mg_file/file/test/test_file.py
mg_file/file/test/test_helpful.py
mg_file/file/test/test_json.py
mg_file/file/test/test_pickle.py
mg_file/file/txt_file.py
mg_file/file/yaml_file.py
mg_file/file/zip_file.py
mg_file/pcos/__init__.py
mg_file/pcos/base_pcos.py
mg_file-0.1.27.dist-info/WHEEL
mg_file-0.1.27.dist-info/METADATA
mg_file-0.1.27.dist-info/RECORD
